{"box_data": [{"position": {"minX": 76.0, "minY": 333.0, "maxX": 106.625, "maxY": 374.0}, "class_id": 0, "box_caption": "fire 0.386", "scores": {"class_score": 0.385986328125}, "domain": "pixel"}, {"position": {"minX": 177.125, "minY": 325.0, "maxX": 281.0, "maxY": 378.5}, "class_id": 0, "box_caption": "fire 0.352", "scores": {"class_score": 0.35205078125}, "domain": "pixel"}, {"position": {"minX": 370.5, "minY": 147.25, "maxX": 421.5, "maxY": 223.5}, "class_id": 0, "box_caption": "fire 0.333", "scores": {"class_score": 0.33251953125}, "domain": "pixel"}, {"position": {"minX": 222.5, "minY": 329.25, "maxX": 265.5, "maxY": 375.25}, "class_id": 0, "box_caption": "fire 0.325", "scores": {"class_score": 0.325439453125}, "domain": "pixel"}, {"position": {"minX": 262.5, "minY": 168.75, "maxX": 380.5, "maxY": 314.0}, "class_id": 0, "box_caption": "fire 0.308", "scores": {"class_score": 0.30810546875}, "domain": "pixel"}, {"position": {"minX": 92.25, "minY": 324.25, "maxX": 207.5, "maxY": 394.25}, "class_id": 0, "box_caption": "fire 0.289", "scores": {"class_score": 0.2890625}, "domain": "pixel"}, {"position": {"minX": 255.25, "minY": 143.75, "maxX": 448.75, "maxY": 328.5}, "class_id": 0, "box_caption": "fire 0.285", "scores": {"class_score": 0.28466796875}, "domain": "pixel"}, {"position": {"minX": 232.625, "minY": 11.5625, "maxX": 311.0, "maxY": 60.875}, "class_id": 0, "box_caption": "fire 0.266", "scores": {"class_score": 0.266357421875}, "domain": "pixel"}, {"position": {"minX": 141.375, "minY": 314.0, "maxX": 277.5, "maxY": 397.0}, "class_id": 0, "box_caption": "fire 0.257", "scores": {"class_score": 0.256591796875}, "domain": "pixel"}, {"position": {"minX": 8.09375, "minY": 306.0, "maxX": 96.625, "maxY": 382.0}, "class_id": 0, "box_caption": "fire 0.255", "scores": {"class_score": 0.254638671875}, "domain": "pixel"}, {"position": {"minX": 48.1875, "minY": 312.75, "maxX": 187.5, "maxY": 383.25}, "class_id": 0, "box_caption": "fire 0.247", "scores": {"class_score": 0.247314453125}, "domain": "pixel"}, {"position": {"minX": 107.375, "minY": 319.75, "maxX": 247.375, "maxY": 396.75}, "class_id": 0, "box_caption": "fire 0.236", "scores": {"class_score": 0.2362060546875}, "domain": "pixel"}, {"position": {"minX": 65.5, "minY": 327.0, "maxX": 113.375, "maxY": 375.5}, "class_id": 0, "box_caption": "fire 0.216", "scores": {"class_score": 0.215576171875}, "domain": "pixel"}, {"position": {"minX": 109.625, "minY": 333.5, "maxX": 192.375, "maxY": 391.0}, "class_id": 0, "box_caption": "fire 0.208", "scores": {"class_score": 0.207763671875}, "domain": "pixel"}, {"position": {"minX": 248.5, "minY": 13.921875, "maxX": 339.0, "maxY": 73.8125}, "class_id": 0, "box_caption": "fire 0.187", "scores": {"class_score": 0.1871337890625}, "domain": "pixel"}, {"position": {"minX": 248.375, "minY": 164.5, "maxX": 339.5, "maxY": 271.25}, "class_id": 0, "box_caption": "fire 0.185", "scores": {"class_score": 0.1851806640625}, "domain": "pixel"}, {"position": {"minX": 246.5, "minY": 167.375, "maxX": 311.0, "maxY": 246.625}, "class_id": 0, "box_caption": "fire 0.180", "scores": {"class_score": 0.1795654296875}, "domain": "pixel"}, {"position": {"minX": 26.53125, "minY": 314.0, "maxX": 129.875, "maxY": 379.5}, "class_id": 0, "box_caption": "fire 0.161", "scores": {"class_score": 0.160888671875}, "domain": "pixel"}, {"position": {"minX": 233.0, "minY": 15.5625, "maxX": 294.5, "maxY": 53.0625}, "class_id": 0, "box_caption": "fire 0.161", "scores": {"class_score": 0.1607666015625}, "domain": "pixel"}, {"position": {"minX": 286.5, "minY": 236.5, "maxX": 369.0, "maxY": 317.5}, "class_id": 0, "box_caption": "fire 0.157", "scores": {"class_score": 0.1568603515625}, "domain": "pixel"}, {"position": {"minX": 4.25, "minY": 311.5, "maxX": 41.0, "maxY": 376.5}, "class_id": 0, "box_caption": "fire 0.139", "scores": {"class_score": 0.13916015625}, "domain": "pixel"}, {"position": {"minX": 71.8125, "minY": 331.75, "maxX": 127.4375, "maxY": 368.75}, "class_id": 0, "box_caption": "fire 0.138", "scores": {"class_score": 0.1376953125}, "domain": "pixel"}, {"position": {"minX": 67.1875, "minY": 322.0, "maxX": 135.75, "maxY": 375.0}, "class_id": 0, "box_caption": "fire 0.132", "scores": {"class_score": 0.131591796875}, "domain": "pixel"}, {"position": {"minX": 230.5, "minY": 332.75, "maxX": 286.0, "maxY": 373.75}, "class_id": 0, "box_caption": "fire 0.128", "scores": {"class_score": 0.1280517578125}, "domain": "pixel"}, {"position": {"minX": 121.125, "minY": 348.75, "maxX": 184.375, "maxY": 380.75}, "class_id": 0, "box_caption": "fire 0.128", "scores": {"class_score": 0.1279296875}, "domain": "pixel"}, {"position": {"minX": 268.0, "minY": 96.4375, "maxX": 312.5, "maxY": 129.25}, "class_id": 0, "box_caption": "fire 0.127", "scores": {"class_score": 0.1265869140625}, "domain": "pixel"}, {"position": {"minX": 246.625, "minY": 174.25, "maxX": 294.0, "maxY": 234.25}, "class_id": 0, "box_caption": "fire 0.124", "scores": {"class_score": 0.12445068359375}, "domain": "pixel"}, {"position": {"minX": 133.625, "minY": 325.5, "maxX": 227.875, "maxY": 391.0}, "class_id": 0, "box_caption": "fire 0.107", "scores": {"class_score": 0.10699462890625}, "domain": "pixel"}, {"position": {"minX": 240.625, "minY": 142.875, "maxX": 322.75, "maxY": 247.125}, "class_id": 0, "box_caption": "fire 0.105", "scores": {"class_score": 0.10528564453125}, "domain": "pixel"}, {"position": {"minX": 69.375, "minY": 344.75, "maxX": 108.0, "maxY": 374.25}, "class_id": 0, "box_caption": "fire 0.104", "scores": {"class_score": 0.10369873046875}, "domain": "pixel"}, {"position": {"minX": 238.25, "minY": 90.75, "maxX": 318.25, "maxY": 134.5}, "class_id": 0, "box_caption": "fire 0.096", "scores": {"class_score": 0.0955810546875}, "domain": "pixel"}, {"position": {"minX": 347.0, "minY": 129.125, "maxX": 434.5, "maxY": 316.0}, "class_id": 0, "box_caption": "fire 0.095", "scores": {"class_score": 0.0953369140625}, "domain": "pixel"}, {"position": {"minX": 130.25, "minY": 343.25, "maxX": 165.25, "maxY": 383.25}, "class_id": 0, "box_caption": "fire 0.093", "scores": {"class_score": 0.0931396484375}, "domain": "pixel"}, {"position": {"minX": 213.75, "minY": 101.375, "maxX": 255.75, "maxY": 146.125}, "class_id": 0, "box_caption": "fire 0.089", "scores": {"class_score": 0.08892822265625}, "domain": "pixel"}, {"position": {"minX": 157.75, "minY": 320.25, "maxX": 246.75, "maxY": 378.25}, "class_id": 0, "box_caption": "fire 0.086", "scores": {"class_score": 0.08624267578125}, "domain": "pixel"}, {"position": {"minX": 293.25, "minY": 258.0, "maxX": 361.75, "maxY": 315.0}, "class_id": 0, "box_caption": "fire 0.080", "scores": {"class_score": 0.080078125}, "domain": "pixel"}, {"position": {"minX": 235.25, "minY": 112.1875, "maxX": 371.25, "maxY": 272.5}, "class_id": 0, "box_caption": "fire 0.080", "scores": {"class_score": 0.0799560546875}, "domain": "pixel"}, {"position": {"minX": 40.4375, "minY": 320.0, "maxX": 117.8125, "maxY": 372.0}, "class_id": 0, "box_caption": "fire 0.077", "scores": {"class_score": 0.07745361328125}, "domain": "pixel"}, {"position": {"minX": 270.25, "minY": 197.75, "maxX": 361.25, "maxY": 320.25}, "class_id": 0, "box_caption": "fire 0.077", "scores": {"class_score": 0.0765380859375}, "domain": "pixel"}, {"position": {"minX": 242.125, "minY": 14.71875, "maxX": 346.0, "maxY": 136.125}, "class_id": 0, "box_caption": "fire 0.075", "scores": {"class_score": 0.07470703125}, "domain": "pixel"}, {"position": {"minX": 259.5, "minY": 188.75, "maxX": 343.5, "maxY": 300.75}, "class_id": 0, "box_caption": "fire 0.073", "scores": {"class_score": 0.07293701171875}, "domain": "pixel"}, {"position": {"minX": 67.1875, "minY": 311.75, "maxX": 233.75, "maxY": 406.25}, "class_id": 0, "box_caption": "fire 0.072", "scores": {"class_score": 0.07177734375}, "domain": "pixel"}, {"position": {"minX": 7.7265625, "minY": 314.25, "maxX": 30.59375, "maxY": 372.75}, "class_id": 0, "box_caption": "fire 0.070", "scores": {"class_score": 0.06988525390625}, "domain": "pixel"}, {"position": {"minX": 333.0, "minY": 209.625, "maxX": 447.0, "maxY": 315.5}, "class_id": 0, "box_caption": "fire 0.070", "scores": {"class_score": 0.06988525390625}, "domain": "pixel"}, {"position": {"minX": 212.0, "minY": 333.5, "maxX": 275.0, "maxY": 383.0}, "class_id": 0, "box_caption": "fire 0.070", "scores": {"class_score": 0.069580078125}, "domain": "pixel"}, {"position": {"minX": 385.25, "minY": 239.25, "maxX": 436.25, "maxY": 308.75}, "class_id": 0, "box_caption": "fire 0.069", "scores": {"class_score": 0.06927490234375}, "domain": "pixel"}, {"position": {"minX": 33.0625, "minY": 296.5, "maxX": 200.75, "maxY": 396.0}, "class_id": 0, "box_caption": "fire 0.069", "scores": {"class_score": 0.06927490234375}, "domain": "pixel"}, {"position": {"minX": 10.2734375, "minY": 309.0, "maxX": 36.3125, "maxY": 358.0}, "class_id": 0, "box_caption": "fire 0.069", "scores": {"class_score": 0.06915283203125}, "domain": "pixel"}, {"position": {"minX": 368.0, "minY": 208.0, "maxX": 437.0, "maxY": 315.0}, "class_id": 0, "box_caption": "fire 0.068", "scores": {"class_score": 0.06817626953125}, "domain": "pixel"}, {"position": {"minX": 369.25, "minY": 148.125, "maxX": 409.25, "maxY": 207.875}, "class_id": 0, "box_caption": "fire 0.067", "scores": {"class_score": 0.06732177734375}, "domain": "pixel"}, {"position": {"minX": 359.75, "minY": 148.25, "maxX": 427.25, "maxY": 273.0}, "class_id": 0, "box_caption": "fire 0.066", "scores": {"class_score": 0.06585693359375}, "domain": "pixel"}, {"position": {"minX": 218.5, "minY": 96.875, "maxX": 276.5, "maxY": 139.5}, "class_id": 0, "box_caption": "fire 0.059", "scores": {"class_score": 0.058624267578125}, "domain": "pixel"}, {"position": {"minX": 285.5, "minY": 28.53125, "maxX": 346.5, "maxY": 73.75}, "class_id": 0, "box_caption": "fire 0.058", "scores": {"class_score": 0.058258056640625}, "domain": "pixel"}, {"position": {"minX": 3.671875, "minY": 307.5, "maxX": 63.5, "maxY": 381.0}, "class_id": 0, "box_caption": "fire 0.058", "scores": {"class_score": 0.05780029296875}, "domain": "pixel"}, {"position": {"minX": 170.625, "minY": 329.0, "maxX": 220.125, "maxY": 381.0}, "class_id": 0, "box_caption": "fire 0.054", "scores": {"class_score": 0.054351806640625}, "domain": "pixel"}, {"position": {"minX": 113.4375, "minY": 345.0, "maxX": 171.0, "maxY": 384.5}, "class_id": 0, "box_caption": "fire 0.054", "scores": {"class_score": 0.05419921875}, "domain": "pixel"}, {"position": {"minX": 407.25, "minY": 267.0, "maxX": 441.75, "maxY": 312.5}, "class_id": 0, "box_caption": "fire 0.054", "scores": {"class_score": 0.053619384765625}, "domain": "pixel"}, {"position": {"minX": 352.25, "minY": 337.5, "maxX": 394.75, "maxY": 370.0}, "class_id": 0, "box_caption": "fire 0.053", "scores": {"class_score": 0.053497314453125}, "domain": "pixel"}, {"position": {"minX": 119.8125, "minY": 336.0, "maxX": 164.25, "maxY": 379.0}, "class_id": 0, "box_caption": "fire 0.053", "scores": {"class_score": 0.053375244140625}, "domain": "pixel"}, {"position": {"minX": 252.625, "minY": 180.75, "maxX": 316.75, "maxY": 269.25}, "class_id": 0, "box_caption": "fire 0.052", "scores": {"class_score": 0.051513671875}, "domain": "pixel"}, {"position": {"minX": 257.75, "minY": 87.4375, "maxX": 327.25, "maxY": 140.125}, "class_id": 0, "box_caption": "fire 0.049", "scores": {"class_score": 0.049072265625}, "domain": "pixel"}, {"position": {"minX": 371.5, "minY": 154.875, "maxX": 434.0, "maxY": 308.5}, "class_id": 0, "box_caption": "fire 0.048", "scores": {"class_score": 0.047607421875}, "domain": "pixel"}, {"position": {"minX": 228.125, "minY": 95.9375, "maxX": 431.0, "maxY": 280.25}, "class_id": 0, "box_caption": "fire 0.044", "scores": {"class_score": 0.04412841796875}, "domain": "pixel"}, {"position": {"minX": 60.21875, "minY": 311.0, "maxX": 109.0, "maxY": 356.0}, "class_id": 0, "box_caption": "fire 0.043", "scores": {"class_score": 0.0430908203125}, "domain": "pixel"}, {"position": {"minX": 348.75, "minY": 139.125, "maxX": 419.75, "maxY": 243.375}, "class_id": 0, "box_caption": "fire 0.043", "scores": {"class_score": 0.042572021484375}, "domain": "pixel"}, {"position": {"minX": 205.0, "minY": -2.5, "maxX": 343.5, "maxY": 156.5}, "class_id": 0, "box_caption": "fire 0.042", "scores": {"class_score": 0.04217529296875}, "domain": "pixel"}, {"position": {"minX": 200.375, "minY": 319.5, "maxX": 297.5, "maxY": 385.0}, "class_id": 0, "box_caption": "fire 0.042", "scores": {"class_score": 0.0418701171875}, "domain": "pixel"}, {"position": {"minX": -2.375, "minY": 292.75, "maxX": 110.0, "maxY": 396.75}, "class_id": 0, "box_caption": "fire 0.041", "scores": {"class_score": 0.04095458984375}, "domain": "pixel"}, {"position": {"minX": 378.0, "minY": 140.0, "maxX": 432.5, "maxY": 241.0}, "class_id": 0, "box_caption": "fire 0.041", "scores": {"class_score": 0.040557861328125}, "domain": "pixel"}, {"position": {"minX": 227.125, "minY": 87.375, "maxX": 337.25, "maxY": 184.125}, "class_id": 0, "box_caption": "fire 0.040", "scores": {"class_score": 0.0401611328125}, "domain": "pixel"}, {"position": {"minX": 267.0, "minY": 185.0, "maxX": 414.0, "maxY": 340.5}, "class_id": 0, "box_caption": "fire 0.039", "scores": {"class_score": 0.039306640625}, "domain": "pixel"}, {"position": {"minX": 69.875, "minY": 327.25, "maxX": 172.25, "maxY": 382.25}, "class_id": 0, "box_caption": "fire 0.039", "scores": {"class_score": 0.038665771484375}, "domain": "pixel"}, {"position": {"minX": 375.0, "minY": 138.75, "maxX": 427.5, "maxY": 206.0}, "class_id": 0, "box_caption": "fire 0.038", "scores": {"class_score": 0.038177490234375}, "domain": "pixel"}, {"position": {"minX": 265.75, "minY": 221.375, "maxX": 351.25, "maxY": 298.5}, "class_id": 0, "box_caption": "fire 0.038", "scores": {"class_score": 0.0377197265625}, "domain": "pixel"}, {"position": {"minX": 268.0, "minY": 215.5, "maxX": 329.0, "maxY": 288.25}, "class_id": 0, "box_caption": "fire 0.037", "scores": {"class_score": 0.037322998046875}, "domain": "pixel"}, {"position": {"minX": 257.25, "minY": 13.46875, "maxX": 323.25, "maxY": 57.59375}, "class_id": 0, "box_caption": "fire 0.037", "scores": {"class_score": 0.03717041015625}, "domain": "pixel"}, {"position": {"minX": 317.0, "minY": 263.5, "maxX": 375.0, "maxY": 304.0}, "class_id": 0, "box_caption": "fire 0.035", "scores": {"class_score": 0.0350341796875}, "domain": "pixel"}, {"position": {"minX": 210.5, "minY": 4.21875, "maxX": 352.5, "maxY": 94.5}, "class_id": 0, "box_caption": "fire 0.033", "scores": {"class_score": 0.032806396484375}, "domain": "pixel"}, {"position": {"minX": 4.8125, "minY": 331.75, "maxX": 43.59375, "maxY": 393.25}, "class_id": 0, "box_caption": "fire 0.032", "scores": {"class_score": 0.03228759765625}, "domain": "pixel"}, {"position": {"minX": 300.0, "minY": 32.78125, "maxX": 339.5, "maxY": 73.5}, "class_id": 0, "box_caption": "fire 0.032", "scores": {"class_score": 0.032135009765625}, "domain": "pixel"}, {"position": {"minX": 59.9375, "minY": 310.0, "maxX": 144.75, "maxY": 368.0}, "class_id": 0, "box_caption": "fire 0.030", "scores": {"class_score": 0.0300445556640625}, "domain": "pixel"}, {"position": {"minX": 120.125, "minY": 353.75, "maxX": 163.875, "maxY": 381.25}, "class_id": 0, "box_caption": "fire 0.028", "scores": {"class_score": 0.028289794921875}, "domain": "pixel"}, {"position": {"minX": 172.25, "minY": 316.25, "maxX": 235.0, "maxY": 365.75}, "class_id": 0, "box_caption": "fire 0.028", "scores": {"class_score": 0.028228759765625}, "domain": "pixel"}, {"position": {"minX": 241.125, "minY": 173.75, "maxX": 280.25, "maxY": 225.75}, "class_id": 0, "box_caption": "fire 0.027", "scores": {"class_score": 0.02740478515625}, "domain": "pixel"}, {"position": {"minX": 291.0, "minY": 201.25, "maxX": 458.5, "maxY": 326.25}, "class_id": 0, "box_caption": "fire 0.027", "scores": {"class_score": 0.0269927978515625}, "domain": "pixel"}, {"position": {"minX": 149.5, "minY": 339.0, "maxX": 211.5, "maxY": 387.0}, "class_id": 0, "box_caption": "fire 0.027", "scores": {"class_score": 0.0268402099609375}, "domain": "pixel"}, {"position": {"minX": 191.625, "minY": 331.5, "maxX": 263.0, "maxY": 375.0}, "class_id": 0, "box_caption": "fire 0.026", "scores": {"class_score": 0.026153564453125}, "domain": "pixel"}, {"position": {"minX": 273.5, "minY": 88.8125, "maxX": 323.5, "maxY": 130.75}, "class_id": 0, "box_caption": "fire 0.026", "scores": {"class_score": 0.0260772705078125}, "domain": "pixel"}, {"position": {"minX": 414.0, "minY": 274.75, "maxX": 438.0, "maxY": 314.25}, "class_id": 0, "box_caption": "fire 0.026", "scores": {"class_score": 0.0258636474609375}, "domain": "pixel"}, {"position": {"minX": 7.578125, "minY": 304.75, "maxX": 27.609375, "maxY": 358.75}, "class_id": 0, "box_caption": "fire 0.026", "scores": {"class_score": 0.025787353515625}, "domain": "pixel"}, {"position": {"minX": 11.90625, "minY": 307.0, "maxX": 57.15625, "maxY": 355.0}, "class_id": 0, "box_caption": "fire 0.025", "scores": {"class_score": 0.024993896484375}, "domain": "pixel"}, {"position": {"minX": 257.25, "minY": 80.625, "maxX": 349.25, "maxY": 196.125}, "class_id": 0, "box_caption": "fire 0.025", "scores": {"class_score": 0.0245361328125}, "domain": "pixel"}, {"position": {"minX": -8.625, "minY": 309.5, "maxX": 174.25, "maxY": 399.0}, "class_id": 0, "box_caption": "fire 0.024", "scores": {"class_score": 0.0238037109375}, "domain": "pixel"}, {"position": {"minX": 258.25, "minY": 96.0625, "maxX": 299.25, "maxY": 131.75}, "class_id": 0, "box_caption": "fire 0.024", "scores": {"class_score": 0.02374267578125}, "domain": "pixel"}, {"position": {"minX": 293.75, "minY": 249.125, "maxX": 381.25, "maxY": 307.5}, "class_id": 0, "box_caption": "fire 0.024", "scores": {"class_score": 0.02374267578125}, "domain": "pixel"}, {"position": {"minX": 314.25, "minY": 142.375, "maxX": 445.25, "maxY": 287.5}, "class_id": 0, "box_caption": "fire 0.023", "scores": {"class_score": 0.0230560302734375}, "domain": "pixel"}, {"position": {"minX": 167.5, "minY": 313.75, "maxX": 266.75, "maxY": 367.25}, "class_id": 0, "box_caption": "fire 0.023", "scores": {"class_score": 0.022735595703125}, "domain": "pixel"}, {"position": {"minX": 271.5, "minY": 231.375, "maxX": 339.0, "maxY": 315.0}, "class_id": 0, "box_caption": "fire 0.021", "scores": {"class_score": 0.0214080810546875}, "domain": "pixel"}, {"position": {"minX": 219.375, "minY": -9.71875, "maxX": 328.5, "maxY": 74.5}, "class_id": 0, "box_caption": "fire 0.021", "scores": {"class_score": 0.0211944580078125}, "domain": "pixel"}, {"position": {"minX": 209.75, "minY": 93.0, "maxX": 288.25, "maxY": 161.75}, "class_id": 0, "box_caption": "fire 0.021", "scores": {"class_score": 0.0211639404296875}, "domain": "pixel"}, {"position": {"minX": 32.8125, "minY": 304.25, "maxX": 115.3125, "maxY": 362.25}, "class_id": 0, "box_caption": "fire 0.021", "scores": {"class_score": 0.0211181640625}, "domain": "pixel"}, {"position": {"minX": 210.75, "minY": 79.75, "maxX": 356.75, "maxY": 209.75}, "class_id": 0, "box_caption": "fire 0.021", "scores": {"class_score": 0.0209503173828125}, "domain": "pixel"}, {"position": {"minX": 203.75, "minY": 91.0625, "maxX": 259.25, "maxY": 153.25}, "class_id": 0, "box_caption": "fire 0.021", "scores": {"class_score": 0.0207061767578125}, "domain": "pixel"}, {"position": {"minX": 224.25, "minY": 13.234375, "maxX": 268.75, "maxY": 53.5}, "class_id": 0, "box_caption": "fire 0.021", "scores": {"class_score": 0.0206298828125}, "domain": "pixel"}, {"position": {"minX": 247.875, "minY": 341.25, "maxX": 301.25, "maxY": 369.75}, "class_id": 0, "box_caption": "fire 0.021", "scores": {"class_score": 0.0205230712890625}, "domain": "pixel"}, {"position": {"minX": 390.75, "minY": 183.625, "maxX": 436.25, "maxY": 308.0}, "class_id": 0, "box_caption": "fire 0.021", "scores": {"class_score": 0.0205078125}, "domain": "pixel"}, {"position": {"minX": 247.25, "minY": 341.5, "maxX": 283.75, "maxY": 375.5}, "class_id": 0, "box_caption": "fire 0.020", "scores": {"class_score": 0.0204925537109375}, "domain": "pixel"}, {"position": {"minX": 308.25, "minY": 29.65625, "maxX": 348.75, "maxY": 73.0}, "class_id": 0, "box_caption": "fire 0.020", "scores": {"class_score": 0.0204010009765625}, "domain": "pixel"}, {"position": {"minX": 241.75, "minY": 149.75, "maxX": 400.25, "maxY": 292.75}, "class_id": 0, "box_caption": "fire 0.020", "scores": {"class_score": 0.0199127197265625}, "domain": "pixel"}, {"position": {"minX": 338.25, "minY": 129.375, "maxX": 456.75, "maxY": 256.5}, "class_id": 0, "box_caption": "fire 0.020", "scores": {"class_score": 0.01983642578125}, "domain": "pixel"}, {"position": {"minX": 393.25, "minY": 259.25, "maxX": 442.75, "maxY": 308.25}, "class_id": 0, "box_caption": "fire 0.019", "scores": {"class_score": 0.0194549560546875}, "domain": "pixel"}, {"position": {"minX": 369.0, "minY": 138.125, "maxX": 421.0, "maxY": 188.625}, "class_id": 0, "box_caption": "fire 0.019", "scores": {"class_score": 0.0189208984375}, "domain": "pixel"}, {"position": {"minX": 329.75, "minY": 300.0, "maxX": 406.25, "maxY": 376.0}, "class_id": 0, "box_caption": "fire 0.019", "scores": {"class_score": 0.0185546875}, "domain": "pixel"}, {"position": {"minX": 290.25, "minY": 240.0, "maxX": 421.25, "maxY": 314.0}, "class_id": 0, "box_caption": "fire 0.018", "scores": {"class_score": 0.0181121826171875}, "domain": "pixel"}, {"position": {"minX": 303.5, "minY": 269.75, "maxX": 357.5, "maxY": 312.75}, "class_id": 0, "box_caption": "fire 0.018", "scores": {"class_score": 0.0177459716796875}, "domain": "pixel"}, {"position": {"minX": 123.375, "minY": 313.5, "maxX": 204.625, "maxY": 370.0}, "class_id": 0, "box_caption": "fire 0.017", "scores": {"class_score": 0.01739501953125}, "domain": "pixel"}, {"position": {"minX": 130.125, "minY": 308.75, "maxX": 237.625, "maxY": 364.75}, "class_id": 0, "box_caption": "fire 0.016", "scores": {"class_score": 0.0163421630859375}, "domain": "pixel"}, {"position": {"minX": 402.5, "minY": 264.25, "maxX": 433.5, "maxY": 305.25}, "class_id": 0, "box_caption": "fire 0.016", "scores": {"class_score": 0.016326904296875}, "domain": "pixel"}, {"position": {"minX": 204.0, "minY": 317.5, "maxX": 283.25, "maxY": 365.5}, "class_id": 0, "box_caption": "fire 0.016", "scores": {"class_score": 0.01629638671875}, "domain": "pixel"}, {"position": {"minX": 69.3125, "minY": 336.75, "maxX": 123.0625, "maxY": 380.75}, "class_id": 0, "box_caption": "fire 0.016", "scores": {"class_score": 0.0160064697265625}, "domain": "pixel"}, {"position": {"minX": 200.875, "minY": 56.125, "maxX": 346.0, "maxY": 173.5}, "class_id": 0, "box_caption": "fire 0.016", "scores": {"class_score": 0.0157470703125}, "domain": "pixel"}, {"position": {"minX": 325.5, "minY": 267.25, "maxX": 364.5, "maxY": 302.75}, "class_id": 0, "box_caption": "fire 0.015", "scores": {"class_score": 0.01535797119140625}, "domain": "pixel"}, {"position": {"minX": 296.5, "minY": 223.5, "maxX": 382.5, "maxY": 298.0}, "class_id": 0, "box_caption": "fire 0.015", "scores": {"class_score": 0.01531219482421875}, "domain": "pixel"}, {"position": {"minX": 84.125, "minY": 310.0, "maxX": 187.375, "maxY": 358.0}, "class_id": 0, "box_caption": "fire 0.015", "scores": {"class_score": 0.0149688720703125}, "domain": "pixel"}, {"position": {"minX": 362.0, "minY": 144.0, "maxX": 460.0, "maxY": 290.75}, "class_id": 0, "box_caption": "fire 0.015", "scores": {"class_score": 0.01483154296875}, "domain": "pixel"}, {"position": {"minX": 383.25, "minY": 173.25, "maxX": 431.25, "maxY": 246.75}, "class_id": 0, "box_caption": "fire 0.015", "scores": {"class_score": 0.01471710205078125}, "domain": "pixel"}, {"position": {"minX": 242.0, "minY": 335.0, "maxX": 276.0, "maxY": 374.0}, "class_id": 0, "box_caption": "fire 0.014", "scores": {"class_score": 0.0140838623046875}, "domain": "pixel"}, {"position": {"minX": 249.25, "minY": 186.75, "maxX": 300.75, "maxY": 251.75}, "class_id": 0, "box_caption": "fire 0.013", "scores": {"class_score": 0.01348114013671875}, "domain": "pixel"}, {"position": {"minX": 221.75, "minY": 348.75, "maxX": 277.0, "maxY": 375.75}, "class_id": 0, "box_caption": "fire 0.013", "scores": {"class_score": 0.013153076171875}, "domain": "pixel"}, {"position": {"minX": 345.25, "minY": 332.5, "maxX": 388.25, "maxY": 375.0}, "class_id": 0, "box_caption": "fire 0.013", "scores": {"class_score": 0.01300811767578125}, "domain": "pixel"}, {"position": {"minX": 241.875, "minY": 349.0, "maxX": 287.5, "maxY": 372.5}, "class_id": 0, "box_caption": "fire 0.013", "scores": {"class_score": 0.0129852294921875}, "domain": "pixel"}, {"position": {"minX": 150.375, "minY": 328.75, "maxX": 245.375, "maxY": 401.75}, "class_id": 0, "box_caption": "fire 0.013", "scores": {"class_score": 0.01276397705078125}, "domain": "pixel"}, {"position": {"minX": 17.21875, "minY": 299.0, "maxX": 83.375, "maxY": 360.0}, "class_id": 0, "box_caption": "fire 0.013", "scores": {"class_score": 0.0127410888671875}, "domain": "pixel"}, {"position": {"minX": 127.0, "minY": 334.0, "maxX": 180.0, "maxY": 382.0}, "class_id": 0, "box_caption": "fire 0.013", "scores": {"class_score": 0.01267242431640625}, "domain": "pixel"}, {"position": {"minX": 158.875, "minY": 345.0, "maxX": 202.625, "maxY": 382.0}, "class_id": 0, "box_caption": "fire 0.012", "scores": {"class_score": 0.0124969482421875}, "domain": "pixel"}, {"position": {"minX": 203.5, "minY": 338.75, "maxX": 253.0, "maxY": 371.25}, "class_id": 0, "box_caption": "fire 0.012", "scores": {"class_score": 0.01227569580078125}, "domain": "pixel"}, {"position": {"minX": 114.8125, "minY": 315.0, "maxX": 188.0, "maxY": 352.5}, "class_id": 0, "box_caption": "fire 0.012", "scores": {"class_score": 0.012237548828125}, "domain": "pixel"}, {"position": {"minX": 207.25, "minY": 14.640625, "maxX": 277.5, "maxY": 57.25}, "class_id": 0, "box_caption": "fire 0.012", "scores": {"class_score": 0.01216888427734375}, "domain": "pixel"}, {"position": {"minX": 1.0078125, "minY": 15.21875, "maxX": 17.71875, "maxY": 95.25}, "class_id": 0, "box_caption": "fire 0.012", "scores": {"class_score": 0.0117645263671875}, "domain": "pixel"}, {"position": {"minX": 283.5, "minY": 17.40625, "maxX": 352.0, "maxY": 112.625}, "class_id": 0, "box_caption": "fire 0.012", "scores": {"class_score": 0.01172637939453125}, "domain": "pixel"}, {"position": {"minX": 164.25, "minY": 338.25, "maxX": 223.75, "maxY": 399.75}, "class_id": 0, "box_caption": "fire 0.012", "scores": {"class_score": 0.01171875}, "domain": "pixel"}, {"position": {"minX": 189.75, "minY": 303.75, "maxX": 321.25, "maxY": 392.25}, "class_id": 0, "box_caption": "fire 0.012", "scores": {"class_score": 0.01171112060546875}, "domain": "pixel"}, {"position": {"minX": 395.25, "minY": 215.5, "maxX": 442.25, "maxY": 304.0}, "class_id": 0, "box_caption": "fire 0.012", "scores": {"class_score": 0.011627197265625}, "domain": "pixel"}, {"position": {"minX": 277.75, "minY": 261.0, "maxX": 342.25, "maxY": 319.0}, "class_id": 0, "box_caption": "fire 0.012", "scores": {"class_score": 0.01157379150390625}, "domain": "pixel"}, {"position": {"minX": 265.25, "minY": 94.0625, "maxX": 347.75, "maxY": 134.0}, "class_id": 0, "box_caption": "fire 0.012", "scores": {"class_score": 0.011566162109375}, "domain": "pixel"}, {"position": {"minX": 10.515625, "minY": 339.5, "maxX": 53.75, "maxY": 384.5}, "class_id": 0, "box_caption": "fire 0.011", "scores": {"class_score": 0.01146697998046875}, "domain": "pixel"}, {"position": {"minX": 70.375, "minY": 338.0, "maxX": 104.625, "maxY": 387.0}, "class_id": 0, "box_caption": "fire 0.011", "scores": {"class_score": 0.01145172119140625}, "domain": "pixel"}, {"position": {"minX": 71.0, "minY": 313.75, "maxX": 86.875, "maxY": 327.25}, "class_id": 0, "box_caption": "fire 0.011", "scores": {"class_score": 0.0113067626953125}, "domain": "pixel"}, {"position": {"minX": 320.5, "minY": 164.25, "maxX": 436.5, "maxY": 339.25}, "class_id": 0, "box_caption": "fire 0.011", "scores": {"class_score": 0.01126861572265625}, "domain": "pixel"}, {"position": {"minX": 75.875, "minY": 313.75, "maxX": 89.125, "maxY": 326.25}, "class_id": 0, "box_caption": "fire 0.011", "scores": {"class_score": 0.0111236572265625}, "domain": "pixel"}, {"position": {"minX": 243.625, "minY": 15.25, "maxX": 277.25, "maxY": 54.625}, "class_id": 0, "box_caption": "fire 0.011", "scores": {"class_score": 0.0109100341796875}, "domain": "pixel"}, {"position": {"minX": 102.625, "minY": 339.25, "maxX": 203.375, "maxY": 408.25}, "class_id": 0, "box_caption": "fire 0.011", "scores": {"class_score": 0.01070404052734375}, "domain": "pixel"}, {"position": {"minX": 60.84375, "minY": 310.5, "maxX": 91.625, "maxY": 332.5}, "class_id": 0, "box_caption": "fire 0.011", "scores": {"class_score": 0.01068878173828125}, "domain": "pixel"}, {"position": {"minX": 56.6875, "minY": 341.25, "maxX": 189.5, "maxY": 398.25}, "class_id": 0, "box_caption": "fire 0.011", "scores": {"class_score": 0.01067352294921875}, "domain": "pixel"}, {"position": {"minX": 138.0, "minY": 343.75, "maxX": 189.5, "maxY": 386.25}, "class_id": 0, "box_caption": "fire 0.011", "scores": {"class_score": 0.0106353759765625}, "domain": "pixel"}, {"position": {"minX": 355.0, "minY": 326.0, "maxX": 399.0, "maxY": 378.5}, "class_id": 0, "box_caption": "fire 0.010", "scores": {"class_score": 0.010498046875}, "domain": "pixel"}, {"position": {"minX": 126.8125, "minY": 341.0, "maxX": 156.75, "maxY": 375.5}, "class_id": 0, "box_caption": "fire 0.010", "scores": {"class_score": 0.01036834716796875}, "domain": "pixel"}, {"position": {"minX": 346.75, "minY": 236.375, "maxX": 439.25, "maxY": 311.5}, "class_id": 0, "box_caption": "fire 0.010", "scores": {"class_score": 0.01029205322265625}, "domain": "pixel"}, {"position": {"minX": 221.0, "minY": -14.515625, "maxX": 306.5, "maxY": 50.625}, "class_id": 0, "box_caption": "fire 0.010", "scores": {"class_score": 0.01023101806640625}, "domain": "pixel"}, {"position": {"minX": 384.5, "minY": 152.375, "maxX": 437.5, "maxY": 272.25}, "class_id": 0, "box_caption": "fire 0.010", "scores": {"class_score": 0.0101318359375}, "domain": "pixel"}, {"position": {"minX": 0.6796875, "minY": 38.65625, "maxX": 17.09375, "maxY": 133.0}, "class_id": 0, "box_caption": "fire 0.010", "scores": {"class_score": 0.009979248046875}, "domain": "pixel"}, {"position": {"minX": 175.5, "minY": 326.0, "maxX": 295.25, "maxY": 408.0}, "class_id": 0, "box_caption": "fire 0.010", "scores": {"class_score": 0.00995635986328125}, "domain": "pixel"}, {"position": {"minX": 15.375, "minY": 304.75, "maxX": 33.65625, "maxY": 337.25}, "class_id": 0, "box_caption": "fire 0.010", "scores": {"class_score": 0.00980377197265625}, "domain": "pixel"}, {"position": {"minX": 238.25, "minY": 206.5, "maxX": 394.25, "maxY": 362.0}, "class_id": 0, "box_caption": "fire 0.010", "scores": {"class_score": 0.0096893310546875}, "domain": "pixel"}, {"position": {"minX": 396.5, "minY": 269.25, "maxX": 449.0, "maxY": 320.25}, "class_id": 0, "box_caption": "fire 0.010", "scores": {"class_score": 0.00957489013671875}, "domain": "pixel"}, {"position": {"minX": 272.5, "minY": 228.25, "maxX": 317.0, "maxY": 291.25}, "class_id": 0, "box_caption": "fire 0.010", "scores": {"class_score": 0.00955963134765625}, "domain": "pixel"}, {"position": {"minX": 0.7890625, "minY": 70.6875, "maxX": 17.09375, "maxY": 164.75}, "class_id": 0, "box_caption": "fire 0.009", "scores": {"class_score": 0.009490966796875}, "domain": "pixel"}, {"position": {"minX": 408.0, "minY": 221.75, "maxX": 440.0, "maxY": 294.25}, "class_id": 0, "box_caption": "fire 0.009", "scores": {"class_score": 0.00948333740234375}, "domain": "pixel"}, {"position": {"minX": 187.75, "minY": 196.875, "maxX": 356.75, "maxY": 419.0}, "class_id": 0, "box_caption": "fire 0.009", "scores": {"class_score": 0.009429931640625}, "domain": "pixel"}, {"position": {"minX": 267.0, "minY": 10.078125, "maxX": 348.0, "maxY": 64.625}, "class_id": 0, "box_caption": "fire 0.009", "scores": {"class_score": 0.00934600830078125}, "domain": "pixel"}, {"position": {"minX": 201.25, "minY": 106.125, "maxX": 249.25, "maxY": 153.875}, "class_id": 0, "box_caption": "fire 0.009", "scores": {"class_score": 0.0092926025390625}, "domain": "pixel"}, {"position": {"minX": 208.75, "minY": 344.5, "maxX": 264.75, "maxY": 377.5}, "class_id": 0, "box_caption": "fire 0.009", "scores": {"class_score": 0.00923919677734375}, "domain": "pixel"}, {"position": {"minX": 345.25, "minY": 286.5, "maxX": 427.25, "maxY": 383.5}, "class_id": 0, "box_caption": "fire 0.009", "scores": {"class_score": 0.00916290283203125}, "domain": "pixel"}, {"position": {"minX": 234.875, "minY": 333.25, "maxX": 265.0, "maxY": 365.75}, "class_id": 0, "box_caption": "fire 0.009", "scores": {"class_score": 0.00911712646484375}, "domain": "pixel"}, {"position": {"minX": 212.375, "minY": 85.1875, "maxX": 328.0, "maxY": 142.0}, "class_id": 0, "box_caption": "fire 0.009", "scores": {"class_score": 0.0090179443359375}, "domain": "pixel"}, {"position": {"minX": 296.75, "minY": 151.875, "maxX": 414.25, "maxY": 322.0}, "class_id": 0, "box_caption": "fire 0.009", "scores": {"class_score": 0.0088958740234375}, "domain": "pixel"}, {"position": {"minX": 127.25, "minY": 350.0, "maxX": 156.0, "maxY": 384.5}, "class_id": 0, "box_caption": "fire 0.009", "scores": {"class_score": 0.00876617431640625}, "domain": "pixel"}, {"position": {"minX": -0.234375, "minY": 17.65625, "maxX": 36.375, "maxY": 91.625}, "class_id": 0, "box_caption": "fire 0.009", "scores": {"class_score": 0.00873565673828125}, "domain": "pixel"}, {"position": {"minX": 233.875, "minY": 165.125, "maxX": 283.0, "maxY": 216.375}, "class_id": 0, "box_caption": "fire 0.009", "scores": {"class_score": 0.00872039794921875}, "domain": "pixel"}, {"position": {"minX": 100.875, "minY": 325.25, "maxX": 181.125, "maxY": 373.75}, "class_id": 0, "box_caption": "fire 0.009", "scores": {"class_score": 0.00868988037109375}, "domain": "pixel"}, {"position": {"minX": 258.0, "minY": 198.375, "maxX": 338.5, "maxY": 269.25}, "class_id": 0, "box_caption": "fire 0.008", "scores": {"class_score": 0.00817108154296875}, "domain": "pixel"}, {"position": {"minX": -48.34375, "minY": 284.5, "maxX": 96.0, "maxY": 399.5}, "class_id": 0, "box_caption": "fire 0.008", "scores": {"class_score": 0.00817108154296875}, "domain": "pixel"}, {"position": {"minX": 1.16796875, "minY": 103.0625, "maxX": 16.984375, "maxY": 196.5}, "class_id": 0, "box_caption": "fire 0.008", "scores": {"class_score": 0.0081329345703125}, "domain": "pixel"}, {"position": {"minX": 174.375, "minY": 78.5, "maxX": 332.5, "maxY": 188.5}, "class_id": 0, "box_caption": "fire 0.008", "scores": {"class_score": 0.00798797607421875}, "domain": "pixel"}, {"position": {"minX": 235.25, "minY": 338.75, "maxX": 302.25, "maxY": 379.25}, "class_id": 0, "box_caption": "fire 0.008", "scores": {"class_score": 0.0079803466796875}, "domain": "pixel"}, {"position": {"minX": 272.5, "minY": 81.8125, "maxX": 313.5, "maxY": 123.1875}, "class_id": 0, "box_caption": "fire 0.008", "scores": {"class_score": 0.0078887939453125}, "domain": "pixel"}, {"position": {"minX": 372.5, "minY": 157.125, "maxX": 403.5, "maxY": 199.625}, "class_id": 0, "box_caption": "fire 0.008", "scores": {"class_score": 0.00787353515625}, "domain": "pixel"}, {"position": {"minX": 282.0, "minY": 265.0, "maxX": 454.0, "maxY": 399.5}, "class_id": 0, "box_caption": "fire 0.008", "scores": {"class_score": 0.0076141357421875}, "domain": "pixel"}, {"position": {"minX": 193.625, "minY": 328.5, "maxX": 245.875, "maxY": 368.0}, "class_id": 0, "box_caption": "fire 0.008", "scores": {"class_score": 0.007587432861328125}, "domain": "pixel"}, {"position": {"minX": 1.453125, "minY": 22.0625, "maxX": 34.375, "maxY": 125.9375}, "class_id": 0, "box_caption": "fire 0.008", "scores": {"class_score": 0.007564544677734375}, "domain": "pixel"}, {"position": {"minX": 255.125, "minY": 27.09375, "maxX": 309.0, "maxY": 56.40625}, "class_id": 0, "box_caption": "fire 0.007", "scores": {"class_score": 0.007415771484375}, "domain": "pixel"}, {"position": {"minX": 254.0, "minY": 88.75, "maxX": 396.5, "maxY": 205.75}, "class_id": 0, "box_caption": "fire 0.007", "scores": {"class_score": 0.007396697998046875}, "domain": "pixel"}, {"position": {"minX": 11.34375, "minY": 309.25, "maxX": 27.21875, "maxY": 330.75}, "class_id": 0, "box_caption": "fire 0.007", "scores": {"class_score": 0.00737762451171875}, "domain": "pixel"}, {"position": {"minX": 332.75, "minY": 270.5, "maxX": 358.75, "maxY": 300.5}, "class_id": 0, "box_caption": "fire 0.007", "scores": {"class_score": 0.0073699951171875}, "domain": "pixel"}, {"position": {"minX": 150.125, "minY": 291.75, "maxX": 272.0, "maxY": 371.25}, "class_id": 0, "box_caption": "fire 0.007", "scores": {"class_score": 0.007354736328125}, "domain": "pixel"}, {"position": {"minX": 401.0, "minY": 244.25, "maxX": 441.5, "maxY": 319.75}, "class_id": 0, "box_caption": "fire 0.007", "scores": {"class_score": 0.00731658935546875}, "domain": "pixel"}, {"position": {"minX": 54.03125, "minY": 292.75, "maxX": 177.875, "maxY": 369.25}, "class_id": 0, "box_caption": "fire 0.007", "scores": {"class_score": 0.007274627685546875}, "domain": "pixel"}, {"position": {"minX": 224.5, "minY": 95.875, "maxX": 338.0, "maxY": 249.125}, "class_id": 0, "box_caption": "fire 0.007", "scores": {"class_score": 0.00727081298828125}, "domain": "pixel"}, {"position": {"minX": 161.5, "minY": 348.75, "maxX": 213.5, "maxY": 392.25}, "class_id": 0, "box_caption": "fire 0.007", "scores": {"class_score": 0.00725555419921875}, "domain": "pixel"}, {"position": {"minX": 225.625, "minY": 337.0, "maxX": 293.5, "maxY": 392.0}, "class_id": 0, "box_caption": "fire 0.007", "scores": {"class_score": 0.007205963134765625}, "domain": "pixel"}, {"position": {"minX": 411.25, "minY": 233.0, "maxX": 446.25, "maxY": 318.5}, "class_id": 0, "box_caption": "fire 0.007", "scores": {"class_score": 0.007183074951171875}, "domain": "pixel"}, {"position": {"minX": 370.75, "minY": 163.875, "maxX": 424.75, "maxY": 254.625}, "class_id": 0, "box_caption": "fire 0.007", "scores": {"class_score": 0.007114410400390625}, "domain": "pixel"}, {"position": {"minX": 125.375, "minY": 327.0, "maxX": 280.0, "maxY": 421.0}, "class_id": 0, "box_caption": "fire 0.007", "scores": {"class_score": 0.00710296630859375}, "domain": "pixel"}, {"position": {"minX": 263.5, "minY": 26.875, "maxX": 330.5, "maxY": 161.0}, "class_id": 0, "box_caption": "fire 0.007", "scores": {"class_score": 0.007022857666015625}, "domain": "pixel"}, {"position": {"minX": 120.625, "minY": 342.75, "maxX": 219.125, "maxY": 394.25}, "class_id": 0, "box_caption": "fire 0.007", "scores": {"class_score": 0.00701141357421875}, "domain": "pixel"}, {"position": {"minX": 266.0, "minY": 16.078125, "maxX": 299.5, "maxY": 53.0625}, "class_id": 0, "box_caption": "fire 0.007", "scores": {"class_score": 0.006938934326171875}, "domain": "pixel"}, {"position": {"minX": 1.56640625, "minY": 136.25, "maxX": 16.9375, "maxY": 227.75}, "class_id": 0, "box_caption": "fire 0.007", "scores": {"class_score": 0.006908416748046875}, "domain": "pixel"}, {"position": {"minX": 271.25, "minY": 96.9375, "maxX": 302.25, "maxY": 124.1875}, "class_id": 0, "box_caption": "fire 0.007", "scores": {"class_score": 0.0068817138671875}, "domain": "pixel"}, {"position": {"minX": 125.875, "minY": 306.75, "maxX": 181.125, "maxY": 339.25}, "class_id": 0, "box_caption": "fire 0.007", "scores": {"class_score": 0.006870269775390625}, "domain": "pixel"}, {"position": {"minX": 212.75, "minY": 302.5, "maxX": 301.75, "maxY": 371.0}, "class_id": 0, "box_caption": "fire 0.007", "scores": {"class_score": 0.006847381591796875}, "domain": "pixel"}, {"position": {"minX": 303.0, "minY": 248.25, "maxX": 358.0, "maxY": 303.75}, "class_id": 0, "box_caption": "fire 0.007", "scores": {"class_score": 0.006771087646484375}, "domain": "pixel"}, {"position": {"minX": 316.5, "minY": 275.5, "maxX": 374.5, "maxY": 314.5}, "class_id": 0, "box_caption": "fire 0.007", "scores": {"class_score": 0.00666046142578125}, "domain": "pixel"}, {"position": {"minX": 71.6875, "minY": 312.75, "maxX": 92.6875, "maxY": 331.75}, "class_id": 0, "box_caption": "fire 0.007", "scores": {"class_score": 0.006626129150390625}, "domain": "pixel"}, {"position": {"minX": 268.75, "minY": 77.9375, "maxX": 358.25, "maxY": 148.25}, "class_id": 0, "box_caption": "fire 0.006", "scores": {"class_score": 0.00634002685546875}, "domain": "pixel"}, {"position": {"minX": 175.75, "minY": 269.75, "maxX": 299.5, "maxY": 392.25}, "class_id": 0, "box_caption": "fire 0.006", "scores": {"class_score": 0.006336212158203125}, "domain": "pixel"}, {"position": {"minX": 218.5, "minY": 128.0, "maxX": 303.0, "maxY": 235.75}, "class_id": 0, "box_caption": "fire 0.006", "scores": {"class_score": 0.006237030029296875}, "domain": "pixel"}, {"position": {"minX": 151.125, "minY": 310.25, "maxX": 182.625, "maxY": 334.75}, "class_id": 0, "box_caption": "fire 0.006", "scores": {"class_score": 0.0061798095703125}, "domain": "pixel"}, {"position": {"minX": 294.0, "minY": 267.5, "maxX": 343.5, "maxY": 335.5}, "class_id": 0, "box_caption": "fire 0.006", "scores": {"class_score": 0.00617218017578125}, "domain": "pixel"}, {"position": {"minX": 2.91015625, "minY": 18.875, "maxX": 15.3125, "maxY": 121.5}, "class_id": 0, "box_caption": "fire 0.006", "scores": {"class_score": 0.006160736083984375}, "domain": "pixel"}, {"position": {"minX": 66.875, "minY": 332.75, "maxX": 137.375, "maxY": 394.75}, "class_id": 0, "box_caption": "fire 0.006", "scores": {"class_score": 0.006153106689453125}, "domain": "pixel"}, {"position": {"minX": 324.5, "minY": 114.625, "maxX": 431.0, "maxY": 210.875}, "class_id": 0, "box_caption": "fire 0.006", "scores": {"class_score": 0.006134033203125}, "domain": "pixel"}, {"position": {"minX": 285.5, "minY": 267.5, "maxX": 422.5, "maxY": 307.0}, "class_id": 0, "box_caption": "fire 0.006", "scores": {"class_score": 0.006084442138671875}, "domain": "pixel"}, {"position": {"minX": 350.5, "minY": 337.25, "maxX": 416.5, "maxY": 373.75}, "class_id": 0, "box_caption": "fire 0.006", "scores": {"class_score": 0.006072998046875}, "domain": "pixel"}, {"position": {"minX": 0.578125, "minY": 48.46875, "maxX": 33.9375, "maxY": 160.75}, "class_id": 0, "box_caption": "fire 0.006", "scores": {"class_score": 0.006061553955078125}, "domain": "pixel"}, {"position": {"minX": 247.0, "minY": 5.1875, "maxX": 393.5, "maxY": 143.0}, "class_id": 0, "box_caption": "fire 0.006", "scores": {"class_score": 0.006061553955078125}, "domain": "pixel"}, {"position": {"minX": 217.0, "minY": 221.5, "maxX": 341.0, "maxY": 400.0}, "class_id": 0, "box_caption": "fire 0.006", "scores": {"class_score": 0.00605010986328125}, "domain": "pixel"}, {"position": {"minX": 381.75, "minY": 261.25, "maxX": 430.25, "maxY": 307.75}, "class_id": 0, "box_caption": "fire 0.006", "scores": {"class_score": 0.006031036376953125}, "domain": "pixel"}, {"position": {"minX": 3.03515625, "minY": 50.3125, "maxX": 15.40625, "maxY": 153.75}, "class_id": 0, "box_caption": "fire 0.006", "scores": {"class_score": 0.005947113037109375}, "domain": "pixel"}, {"position": {"minX": 283.0, "minY": 92.0, "maxX": 313.5, "maxY": 126.25}, "class_id": 0, "box_caption": "fire 0.006", "scores": {"class_score": 0.00589752197265625}, "domain": "pixel"}, {"position": {"minX": 299.25, "minY": 279.0, "maxX": 350.75, "maxY": 319.0}, "class_id": 0, "box_caption": "fire 0.006", "scores": {"class_score": 0.00588226318359375}, "domain": "pixel"}, {"position": {"minX": 114.75, "minY": 183.625, "maxX": 176.5, "maxY": 219.125}, "class_id": 0, "box_caption": "fire 0.006", "scores": {"class_score": 0.0058441162109375}, "domain": "pixel"}, {"position": {"minX": 383.5, "minY": 152.0, "maxX": 429.5, "maxY": 222.0}, "class_id": 0, "box_caption": "fire 0.006", "scores": {"class_score": 0.005832672119140625}, "domain": "pixel"}, {"position": {"minX": 81.75, "minY": 285.75, "maxX": 209.5, "maxY": 378.25}, "class_id": 0, "box_caption": "fire 0.006", "scores": {"class_score": 0.005828857421875}, "domain": "pixel"}, {"position": {"minX": 179.375, "minY": 335.5, "maxX": 211.125, "maxY": 375.5}, "class_id": 0, "box_caption": "fire 0.006", "scores": {"class_score": 0.0058135986328125}, "domain": "pixel"}, {"position": {"minX": 231.75, "minY": 27.15625, "maxX": 286.75, "maxY": 53.84375}, "class_id": 0, "box_caption": "fire 0.006", "scores": {"class_score": 0.005741119384765625}, "domain": "pixel"}, {"position": {"minX": 1.546875, "minY": 288.75, "maxX": 48.125, "maxY": 360.75}, "class_id": 0, "box_caption": "fire 0.006", "scores": {"class_score": 0.00569915771484375}, "domain": "pixel"}, {"position": {"minX": 263.25, "minY": 0.15625, "maxX": 385.25, "maxY": 107.125}, "class_id": 0, "box_caption": "fire 0.006", "scores": {"class_score": 0.00568389892578125}, "domain": "pixel"}, {"position": {"minX": 351.5, "minY": 263.5, "maxX": 438.0, "maxY": 312.0}, "class_id": 0, "box_caption": "fire 0.006", "scores": {"class_score": 0.005611419677734375}, "domain": "pixel"}, {"position": {"minX": 11.6875, "minY": 341.5, "maxX": 39.0, "maxY": 385.0}, "class_id": 0, "box_caption": "fire 0.006", "scores": {"class_score": 0.005596160888671875}, "domain": "pixel"}, {"position": {"minX": 11.484375, "minY": 297.5, "maxX": 39.5, "maxY": 346.0}, "class_id": 0, "box_caption": "fire 0.006", "scores": {"class_score": 0.005573272705078125}, "domain": "pixel"}, {"position": {"minX": 55.0625, "minY": 305.25, "maxX": 97.1875, "maxY": 339.25}, "class_id": 0, "box_caption": "fire 0.005", "scores": {"class_score": 0.005413055419921875}, "domain": "pixel"}, {"position": {"minX": 2.94921875, "minY": 82.5, "maxX": 15.359375, "maxY": 185.5}, "class_id": 0, "box_caption": "fire 0.005", "scores": {"class_score": 0.005336761474609375}, "domain": "pixel"}, {"position": {"minX": 24.375, "minY": 306.75, "maxX": 55.0, "maxY": 335.25}, "class_id": 0, "box_caption": "fire 0.005", "scores": {"class_score": 0.005313873291015625}, "domain": "pixel"}, {"position": {"minX": 76.25, "minY": 323.5, "maxX": 106.0, "maxY": 360.0}, "class_id": 0, "box_caption": "fire 0.005", "scores": {"class_score": 0.0052642822265625}, "domain": "pixel"}, {"position": {"minX": 381.0, "minY": 136.75, "maxX": 436.5, "maxY": 190.75}, "class_id": 0, "box_caption": "fire 0.005", "scores": {"class_score": 0.0052337646484375}, "domain": "pixel"}, {"position": {"minX": 233.5, "minY": 176.5, "maxX": 284.0, "maxY": 249.25}, "class_id": 0, "box_caption": "fire 0.005", "scores": {"class_score": 0.0052032470703125}, "domain": "pixel"}, {"position": {"minX": 226.5, "minY": 165.75, "maxX": 360.5, "maxY": 354.75}, "class_id": 0, "box_caption": "fire 0.005", "scores": {"class_score": 0.005191802978515625}, "domain": "pixel"}, {"position": {"minX": 0.609375, "minY": 80.375, "maxX": 33.9375, "maxY": 191.375}, "class_id": 0, "box_caption": "fire 0.005", "scores": {"class_score": 0.005168914794921875}, "domain": "pixel"}, {"position": {"minX": 291.0, "minY": 258.5, "maxX": 404.0, "maxY": 376.5}, "class_id": 0, "box_caption": "fire 0.005", "scores": {"class_score": 0.005123138427734375}, "domain": "pixel"}, {"position": {"minX": 299.25, "minY": 188.375, "maxX": 346.25, "maxY": 232.625}, "class_id": 0, "box_caption": "fire 0.005", "scores": {"class_score": 0.005077362060546875}, "domain": "pixel"}, {"position": {"minX": 250.125, "minY": 11.1875, "maxX": 303.0, "maxY": 48.6875}, "class_id": 0, "box_caption": "fire 0.005", "scores": {"class_score": 0.005046844482421875}, "domain": "pixel"}, {"position": {"minX": 139.0, "minY": 316.0, "maxX": 188.5, "maxY": 365.5}, "class_id": 0, "box_caption": "fire 0.005", "scores": {"class_score": 0.004932403564453125}, "domain": "pixel"}, {"position": {"minX": 240.5, "minY": 158.25, "maxX": 296.5, "maxY": 221.0}, "class_id": 0, "box_caption": "fire 0.005", "scores": {"class_score": 0.0048980712890625}, "domain": "pixel"}, {"position": {"minX": 351.25, "minY": 133.5, "maxX": 411.75, "maxY": 188.75}, "class_id": 0, "box_caption": "fire 0.005", "scores": {"class_score": 0.004894256591796875}, "domain": "pixel"}, {"position": {"minX": 253.625, "minY": 200.75, "maxX": 303.5, "maxY": 267.0}, "class_id": 0, "box_caption": "fire 0.005", "scores": {"class_score": 0.00487518310546875}, "domain": "pixel"}, {"position": {"minX": 252.125, "minY": 53.25, "maxX": 318.25, "maxY": 139.0}, "class_id": 0, "box_caption": "fire 0.005", "scores": {"class_score": 0.004871368408203125}, "domain": "pixel"}, {"position": {"minX": 259.5, "minY": 181.0, "maxX": 351.0, "maxY": 257.25}, "class_id": 0, "box_caption": "fire 0.005", "scores": {"class_score": 0.00482940673828125}, "domain": "pixel"}, {"position": {"minX": 289.0, "minY": 279.5, "maxX": 334.0, "maxY": 318.0}, "class_id": 0, "box_caption": "fire 0.005", "scores": {"class_score": 0.00481414794921875}, "domain": "pixel"}, {"position": {"minX": 416.5, "minY": 272.25, "maxX": 447.0, "maxY": 322.75}, "class_id": 0, "box_caption": "fire 0.005", "scores": {"class_score": 0.004779815673828125}, "domain": "pixel"}, {"position": {"minX": 127.75, "minY": 318.0, "maxX": 155.75, "maxY": 337.5}, "class_id": 0, "box_caption": "fire 0.005", "scores": {"class_score": 0.004734039306640625}, "domain": "pixel"}, {"position": {"minX": -0.3125, "minY": 328.75, "maxX": 94.0625, "maxY": 421.75}, "class_id": 0, "box_caption": "fire 0.005", "scores": {"class_score": 0.00469970703125}, "domain": "pixel"}, {"position": {"minX": 0.859375, "minY": 116.5, "maxX": 34.3125, "maxY": 216.25}, "class_id": 0, "box_caption": "fire 0.005", "scores": {"class_score": 0.0046844482421875}, "domain": "pixel"}, {"position": {"minX": 2.578125, "minY": 16.8125, "maxX": 23.765625, "maxY": 65.3125}, "class_id": 0, "box_caption": "fire 0.005", "scores": {"class_score": 0.004589080810546875}, "domain": "pixel"}, {"position": {"minX": 377.0, "minY": 132.25, "maxX": 449.0, "maxY": 210.0}, "class_id": 0, "box_caption": "fire 0.005", "scores": {"class_score": 0.00458526611328125}, "domain": "pixel"}, {"position": {"minX": 262.0, "minY": -1.15625, "maxX": 368.0, "maxY": 73.5}, "class_id": 0, "box_caption": "fire 0.005", "scores": {"class_score": 0.004573822021484375}, "domain": "pixel"}, {"position": {"minX": 211.625, "minY": 108.8125, "maxX": 274.25, "maxY": 149.75}, "class_id": 0, "box_caption": "fire 0.005", "scores": {"class_score": 0.004528045654296875}, "domain": "pixel"}, {"position": {"minX": 96.5, "minY": 269.75, "maxX": 249.25, "maxY": 389.25}, "class_id": 0, "box_caption": "fire 0.005", "scores": {"class_score": 0.004528045654296875}, "domain": "pixel"}, {"position": {"minX": 395.25, "minY": 199.5, "maxX": 438.75, "maxY": 269.5}, "class_id": 0, "box_caption": "fire 0.004", "scores": {"class_score": 0.0044708251953125}, "domain": "pixel"}, {"position": {"minX": 2.90234375, "minY": 115.625, "maxX": 15.21875, "maxY": 216.625}, "class_id": 0, "box_caption": "fire 0.004", "scores": {"class_score": 0.0044403076171875}, "domain": "pixel"}, {"position": {"minX": 200.25, "minY": 87.25, "maxX": 247.25, "maxY": 136.0}, "class_id": 0, "box_caption": "fire 0.004", "scores": {"class_score": 0.00441741943359375}, "domain": "pixel"}, {"position": {"minX": 251.25, "minY": 175.875, "maxX": 283.75, "maxY": 216.125}, "class_id": 0, "box_caption": "fire 0.004", "scores": {"class_score": 0.004405975341796875}, "domain": "pixel"}, {"position": {"minX": 298.5, "minY": 86.1875, "maxX": 440.5, "maxY": 238.25}, "class_id": 0, "box_caption": "fire 0.004", "scores": {"class_score": 0.004398345947265625}, "domain": "pixel"}, {"position": {"minX": 213.625, "minY": 109.625, "maxX": 245.625, "maxY": 147.875}, "class_id": 0, "box_caption": "fire 0.004", "scores": {"class_score": 0.00438690185546875}, "domain": "pixel"}, {"position": {"minX": 81.9375, "minY": 329.0, "maxX": 112.0625, "maxY": 370.0}, "class_id": 0, "box_caption": "fire 0.004", "scores": {"class_score": 0.004367828369140625}, "domain": "pixel"}, {"position": {"minX": 35.3125, "minY": 307.5, "maxX": 74.3125, "maxY": 332.0}, "class_id": 0, "box_caption": "fire 0.004", "scores": {"class_score": 0.004276275634765625}, "domain": "pixel"}, {"position": {"minX": 21.53125, "minY": 311.75, "maxX": 48.71875, "maxY": 334.75}, "class_id": 0, "box_caption": "fire 0.004", "scores": {"class_score": 0.00424957275390625}, "domain": "pixel"}, {"position": {"minX": 258.25, "minY": 343.25, "maxX": 288.75, "maxY": 367.75}, "class_id": 0, "box_caption": "fire 0.004", "scores": {"class_score": 0.00423431396484375}, "domain": "pixel"}, {"position": {"minX": 226.5, "minY": 175.625, "maxX": 301.0, "maxY": 281.25}, "class_id": 0, "box_caption": "fire 0.004", "scores": {"class_score": 0.00423431396484375}, "domain": "pixel"}, {"position": {"minX": 303.5, "minY": 36.3125, "maxX": 360.5, "maxY": 75.0625}, "class_id": 0, "box_caption": "fire 0.004", "scores": {"class_score": 0.004192352294921875}, "domain": "pixel"}, {"position": {"minX": 285.75, "minY": 249.75, "maxX": 341.75, "maxY": 303.25}, "class_id": 0, "box_caption": "fire 0.004", "scores": {"class_score": 0.004177093505859375}, "domain": "pixel"}, {"position": {"minX": 97.75, "minY": 300.25, "maxX": 177.75, "maxY": 345.25}, "class_id": 0, "box_caption": "fire 0.004", "scores": {"class_score": 0.004177093505859375}, "domain": "pixel"}, {"position": {"minX": 224.5, "minY": 335.25, "maxX": 318.5, "maxY": 370.75}, "class_id": 0, "box_caption": "fire 0.004", "scores": {"class_score": 0.004169464111328125}, "domain": "pixel"}, {"position": {"minX": 9.859375, "minY": 326.75, "maxX": 37.125, "maxY": 371.25}, "class_id": 0, "box_caption": "fire 0.004", "scores": {"class_score": 0.004119873046875}, "domain": "pixel"}, {"position": {"minX": 296.75, "minY": 187.75, "maxX": 471.75, "maxY": 379.25}, "class_id": 0, "box_caption": "fire 0.004", "scores": {"class_score": 0.00408935546875}, "domain": "pixel"}, {"position": {"minX": 0.296875, "minY": 33.0, "maxX": 24.828125, "maxY": 105.75}, "class_id": 0, "box_caption": "fire 0.004", "scores": {"class_score": 0.004001617431640625}, "domain": "pixel"}, {"position": {"minX": 249.0, "minY": 97.9375, "maxX": 308.0, "maxY": 138.75}, "class_id": 0, "box_caption": "fire 0.004", "scores": {"class_score": 0.0039825439453125}, "domain": "pixel"}, {"position": {"minX": 166.875, "minY": 314.5, "maxX": 229.125, "maxY": 352.0}, "class_id": 0, "box_caption": "fire 0.004", "scores": {"class_score": 0.003978729248046875}, "domain": "pixel"}, {"position": {"minX": 221.25, "minY": 0.703125, "maxX": 287.25, "maxY": 44.375}, "class_id": 0, "box_caption": "fire 0.004", "scores": {"class_score": 0.003936767578125}, "domain": "pixel"}, {"position": {"minX": 144.5, "minY": 304.0, "maxX": 190.5, "maxY": 343.5}, "class_id": 0, "box_caption": "fire 0.004", "scores": {"class_score": 0.0038890838623046875}, "domain": "pixel"}, {"position": {"minX": 136.25, "minY": 185.5, "maxX": 196.75, "maxY": 220.0}, "class_id": 0, "box_caption": "fire 0.004", "scores": {"class_score": 0.003871917724609375}, "domain": "pixel"}, {"position": {"minX": 3.6796875, "minY": 282.75, "maxX": 24.90625, "maxY": 346.75}, "class_id": 0, "box_caption": "fire 0.004", "scores": {"class_score": 0.0038700103759765625}, "domain": "pixel"}, {"position": {"minX": 121.0, "minY": 346.25, "maxX": 150.0, "maxY": 380.75}, "class_id": 0, "box_caption": "fire 0.004", "scores": {"class_score": 0.0038661956787109375}, "domain": "pixel"}, {"position": {"minX": 283.0, "minY": 158.5, "maxX": 393.5, "maxY": 278.5}, "class_id": 0, "box_caption": "fire 0.004", "scores": {"class_score": 0.0038585662841796875}, "domain": "pixel"}, {"position": {"minX": 237.5, "minY": 15.828125, "maxX": 270.75, "maxY": 43.375}, "class_id": 0, "box_caption": "fire 0.004", "scores": {"class_score": 0.003849029541015625}, "domain": "pixel"}, {"position": {"minX": 170.25, "minY": 63.0, "maxX": 274.75, "maxY": 173.25}, "class_id": 0, "box_caption": "fire 0.004", "scores": {"class_score": 0.003841400146484375}, "domain": "pixel"}, {"position": {"minX": 182.25, "minY": -10.65625, "maxX": 272.25, "maxY": 55.34375}, "class_id": 0, "box_caption": "fire 0.004", "scores": {"class_score": 0.0038242340087890625}, "domain": "pixel"}, {"position": {"minX": 0.734375, "minY": 65.25, "maxX": 24.453125, "maxY": 137.0}, "class_id": 0, "box_caption": "fire 0.004", "scores": {"class_score": 0.003818511962890625}, "domain": "pixel"}, {"position": {"minX": 246.75, "minY": 86.125, "maxX": 322.75, "maxY": 166.625}, "class_id": 0, "box_caption": "fire 0.004", "scores": {"class_score": 0.0037975311279296875}, "domain": "pixel"}, {"position": {"minX": 405.5, "minY": 266.5, "maxX": 436.0, "maxY": 332.0}, "class_id": 0, "box_caption": "fire 0.004", "scores": {"class_score": 0.0037364959716796875}, "domain": "pixel"}, {"position": {"minX": 114.75, "minY": 355.5, "maxX": 195.25, "maxY": 392.5}, "class_id": 0, "box_caption": "fire 0.004", "scores": {"class_score": 0.0037288665771484375}, "domain": "pixel"}], "class_labels": {"0": "fire"}}